repFind/__init__.py
repFind/repFind.py
repFind-1.0.1.dist-info/METADATA
repFind-1.0.1.dist-info/WHEEL
repFind-1.0.1.dist-info/entry_points.txt
repFind-1.0.1.dist-info/top_level.txt
repFind-1.0.1.dist-info/RECORD
